Workbook

Sheet Proyecto
B2: Dinero e inflación: valor del proyecto
B4: VAN nominal (Q de hoy) | C4: =SUM(C32:G32)-C12 -> 760437.97
B5: VAN real equivalente (Q de hoy) | C5: =SUM(C35:G35)-C12 -> 760437.97
B6: Diferencia de valoración (Q) | C6: =C4-C5 -> 0
B8: Entradas amarillas editables. Años al cierre.
B9: Supuestos académicos. No son pronósticos.
B11: Supuestos en Q del año 0
B12: Inversión inicial | C12: 2400000
B13: Unidades por año | C13: 100000
B14: Precio unitario año 0 | C14: 30
B15: Costo variable unitario año 0 | C15: 18
B16: Costos fijos anuales año 0 | C16: 400000
B17: Rentabilidad real requerida | C17: 0.08
B18: Inflación esperada al evaluar | C18: 0.04
B19: Tasa nominal requerida | C19: =(1+C17)*(1+C18)-1 -> 0.1232
B21: Trayectorias anuales | C21: 1 | D21: 2 | E21: 3 | F21: 4 | G21: 5
B22: Inflación general / deflactor | C22: 0.08 | D22: 0.08 | E22: 0.04 | F22: 0.04 | G22: 0.04
B23: Ajuste del precio de venta | C23: 0.08 | D23: 0.08 | E23: 0.04 | F23: 0.04 | G23: 0.04
B24: Aumento del costo variable | C24: 0.1 | D24: 0.1 | E24: 0.04 | F24: 0.04 | G24: 0.04
B25: Aumento de costos fijos | C25: 0.08 | D25: 0.08 | E25: 0.04 | F25: 0.04 | G25: 0.04
B27: Índice general (año 0 = 1) | C27: =1+C22 -> 1.08 | D27: =C27*(1+D22) -> 1.1664 | E27: =D27*(1+E22) -> 1.213056 | F27: =E27*(1+F22) -> 1.2615782 | G27: =F27*(1+G22) -> 1.3120414
B28: Precio unitario nominal (Q) | C28: =$C$14*(1+C23) -> 32.4 | D28: =C28*(1+D23) -> 34.992 | E28: =D28*(1+E23) -> 36.39168 | F28: =E28*(1+F23) -> 37.847347 | G28: =F28*(1+G23) -> 39.361241
B29: Costo variable unitario nominal (Q) | C29: =$C$15*(1+C24) -> 19.8 | D29: =C29*(1+D24) -> 21.78 | E29: =D29*(1+E24) -> 22.6512 | F29: =E29*(1+F24) -> 23.557248 | G29: =F29*(1+G24) -> 24.499538
B30: Costos fijos nominales (Q) | C30: =$C$16*(1+C25) -> 432000 | D30: =C30*(1+D25) -> 466560 | E30: =D30*(1+E25) -> 485222.4 | F30: =E30*(1+F25) -> 504631.3 | G30: =F30*(1+G25) -> 524816.55
B31: Flujo operativo nominal (Q) | C31: =$C$13*(C28-C29)-C30 -> 828000 | D31: =$C$13*(D28-D29)-D30 -> 854640 | E31: =$C$13*(E28-E29)-E30 -> 888825.6 | F31: =$C$13*(F28-F29)-F30 -> 924378.62 | G31: =$C$13*(G28-G29)-G30 -> 961353.77
B32: Valor presente nominal (Q) | C32: =C31/(1+$C$19)^C$21 -> 737179.49 | D32: =D31/(1+$C$19)^D$21 -> 677437.18 | E32: =E31/(1+$C$19)^E$21 -> 627256.64 | F32: =F31/(1+$C$19)^F$21 -> 580793.19 | G32: =G31/(1+$C$19)^G$21 -> 537771.47
B33: Flujo real (Q del año 0) | C33: =C31/C27 -> 766666.67 | D33: =D31/D27 -> 732716.05 | E33: =E31/E27 -> 732716.05 | F33: =F31/F27 -> 732716.05 | G33: =G31/G27 -> 732716.05
B34: Factor de descuento real acumulado | C34: =(1+$C$19)^C$21/C27 -> 1.04 | D34: =(1+$C$19)^D$21/D27 -> 1.0816 | E34: =(1+$C$19)^E$21/E27 -> 1.168128 | F34: =(1+$C$19)^F$21/F27 -> 1.2615782 | G34: =(1+$C$19)^G$21/G27 -> 1.3625045
B35: Valor presente real (Q del año 0) | C35: =C33/C34 -> 737179.49 | D35: =D33/D34 -> 677437.18 | E35: =E33/E34 -> 627256.64 | F35: =F33/F34 -> 580793.19 | G35: =G33/G34 -> 537771.47
B38: Flujo simplificado antes de deuda. Cobros y pagos ocurren al cierre de cada año.
B39: Sin impuestos, capital de trabajo, reposición ni valor residual. No es una evaluación completa.
B40: La tasa nominal usa inflación esperada. El deflactor usa la trayectoria del escenario.
B41: El factor real equivalente conserva el mismo valor presente incluso si cambia la inflación.
B42: Prueba: cambie costos y precios por separado. Un IPC mayor no fija el precio de cada insumo.

Sheet Credito
B2: Crédito y capacidad de pago
B4: Crédito inicial (Q) | C4: 1200000
B5: Plazo: 5 años. Principal igual cada año.
B6: Tasa nominal base del préstamo | C6: 0.1
B7: Cambio supuesto en tasa líder (p.p.) | C7: 0.02
B8: Fracción de transmisión al préstamo | C8: 0.5
B9: 0 = tasa fija / 1 = tasa variable | C9: 1
B10: Tasa nominal del préstamo aplicada | C10: =C6+C7*C8*C9 -> 0.11
B12: Calendario anual | C12: 1 | D12: 2 | E12: 3 | F12: 4 | G12: 5
B13: Saldo inicial | C13: =$C$4 -> 1200000 | D13: =C17 -> 960000 | E13: =D17 -> 720000 | F13: =E17 -> 480000 | G13: =F17 -> 240000
B14: Amortización de principal | C14: =$C$4/5 -> 240000 | D14: =$C$4/5 -> 240000 | E14: =$C$4/5 -> 240000 | F14: =$C$4/5 -> 240000 | G14: =$C$4/5 -> 240000
B15: Intereses | C15: =C13*$C$10 -> 132000 | D15: =D13*$C$10 -> 105600 | E15: =E13*$C$10 -> 79200 | F15: =F13*$C$10 -> 52800 | G15: =G13*$C$10 -> 26400
B16: Servicio de deuda | C16: =C14+C15 -> 372000 | D16: =D14+D15 -> 345600 | E16: =E14+E15 -> 319200 | F16: =F14+F15 -> 292800 | G16: =G14+G15 -> 266400
B17: Saldo final | C17: =C13-C14 -> 960000 | D17: =D13-D14 -> 720000 | E17: =E13-E14 -> 480000 | F17: =F13-F14 -> 240000 | G17: =G13-G14 -> 0
B19: Flujo operativo disponible | C19: =Proyecto!C31 -> 828000 | D19: =Proyecto!D31 -> 854640 | E19: =Proyecto!E31 -> 888825.6 | F19: =Proyecto!F31 -> 924378.62 | G19: =Proyecto!G31 -> 961353.77
B20: Cobertura de deuda (veces) | C20: =IF(C16=0,"Sin deuda",C19/C16) -> 2.2258065 | D20: =IF(D16=0,"Sin deuda",D19/D16) -> 2.4729167 | E20: =IF(E16=0,"Sin deuda",E19/E16) -> 2.7845414 | F20: =IF(F16=0,"Sin deuda",F19/F16) -> 3.1570308 | G20: =IF(G16=0,"Sin deuda",G19/G16) -> 3.6086853
B21: Efectivo después de deuda | C21: =C19-C16 -> 456000 | D21: =D19-D16 -> 509040 | E21: =E19-E16 -> 569625.6 | F21: =F19-F16 -> 631578.62 | G21: =G19-G16 -> 694953.77
B24: SUPUESTOS DEL CASO
B25: La variación se aplica desde el año 1 a todo el saldo de tasa variable.
B26: La tasa líder, la tasa del préstamo y la tasa de descuento son distintas.
B27: El VAN de Proyecto usa flujo antes de deuda. No reste aquí intereses otra vez.
B28: Cobertura menor que 1: el flujo simplificado no cubre el servicio anual.

Sheet Actividades
B2: Laboratorio: decisiones y evidencia
B4: Trabajo individual: 45 minutos + discusión.
B6: Cuatro experimentos con registro de resultados
B7: Prediga el efecto antes de cambiar celdas.
B9: Registre resultados como valores: son capturas de cada experimento.
B11: El modelo recalcula el experimento activo. El registro conserva los anteriores.
B13: Registro individual | C13: VAN (Q) | D13: Cobertura año 1 | E13: Flujo año 1 (Q) | F13: Qué cambió | G13: Decisión
B14: 1. Base
B15: 2. Sorpresa de costos
B16: 3. Respuesta comercial
B17: 4. Crédito
B20: 1. Base
B21: Todo a 4%. Registre el VAN y la cobertura.
B22: 2. Sorpresa de costos
B23: Años 1 y 2: inflación 8%, precio 4%, CV 10%, CF 8%.
B24: 3. Respuesta comercial
B25: Sobre el caso 2, ajuste precios a 8% en años 1 y 2.
B26: 4. Crédito
B27: Compare tasa fija 0 y variable 1. Mantenga el mismo proyecto.
... B34: Método: Fisher exacto y descuento de flujos al cierre.
