Workbook

Sheet Inicio
A1: LABORATORIO DE APLICACIÓN
A2: Del dato macroeconómico al mercado de un proyecto · Caso ANDAR GT, S.A.
B5: Estimación de la demanda potencial de un proyecto de producción y comercialización de calzado en Guatemala
B8: Datos del estudiante
B9: Nombre | E9: Carné
B10: Fecha | E10: Sección / grupo
B12: Cómo utilizar este archivo
B13: 1. Descargue el archivo de Equilibrios de oferta y utilización del Banco de Guatemala y localice el producto P062: Calzado y sus partes.
B14: 2. Complete únicamente las celdas crema. Las celdas verdes contienen fórmulas y se calculan automáticamente.
B15: 3. Los supuestos académicos aparecen en azul claro y pueden modificarse para análisis de sensibilidad.
B16: 4. Utilice los espacios blancos para justificar decisiones, explicar resultados y redactar conclusiones.
B17: 5. Mantenga la unidad del Banguat en millones de quetzales, salvo que la hoja indique expresamente otra unidad.
B19: Leyenda visual
B20: Celda para completar | D20: Ingrese el dato obtenido de la fuente estadística o el valor solicitado.
B21: Fórmula / resultado automático | D21: No sobrescriba estas celdas; contienen fórmulas vinculadas entre etapas.
B22: Supuesto académico del caso | D22: Datos ficticios del laboratorio; pueden utilizarse para sensibilidad.
B23: Comentario / conclusión | D23: Espacio para interpretar resultados, justificar decisiones o redactar conclusiones.
B25: Fuente estadística
B26: Banco de Guatemala · Equilibrios de oferta y utilización · Producto P062: Calzado y sus partes, de cualquier material y de cualquier uso. Sitio institucional: https://www.banguat.gob.gt/

Sheet Etapa1_Datos
A1: ETAPA 1 · LEER EL EQUILIBRIO
A2: Producto P062 · cifras en millones de quetzales
A5: Complete con cifras del Banco de Guatemala
B6: =MATCH($A8,'[1]Equilibrio Oferta-Utilización'!$B$11:$O$11,0) -> 1
A7: Concepto | B7: 2013 | C7: 2019 | D7: 2020 | E7: 2023 p/ | F7: 2024 p/
A8: Producción (PB) | B8: =HLOOKUP(B$7,'[1]Equilibrio Oferta-Utilización'!$D$10:$O$26,MATCH($A8,'[1]Equilibrio Oferta-Utilización'!$B$10:$B$26,0),0) -> 1371.704 | C8: =HLOOKUP(C$7,'[1]Equilibrio Oferta-Utilización'!$D$10:$O$26,MATCH($A8,'[1]Equilibrio Oferta-Utilización'!$B$10:$B$26,0),0) -> 1396.217 | D8: =HLOOKUP(D$7,'[1]Equilibrio Oferta-Utilización'!$D$10:$O$26,MATCH($A8,'[1]Equilibrio Oferta-Utilización'!$B$10:$B$26,0),0) -> 1239.4823 | E8: =HLOOKUP(E$7,'[1]Equilibrio Oferta-Utilización'!$D$10:$O$26,MATCH($A8,'[1]Equilibrio Oferta-Utilización'!$B$10:$B$26,0),0) -> 1767.3027 | F8: =HLOOKUP(F$7,'[1]Equilibrio Oferta-Utilización'!$D$10:$O$26,MATCH($A8,'[1]Equilibrio Oferta-Utilización'!$B$10:$B$26,0),0) -> 1867.0316
A9: Importaciones (CIF) | B9: =HLOOKUP(B$7,'[1]Equilibrio Oferta-Utilización'!$D$10:$O$26,MATCH($A9,'[1]Equilibrio Oferta-Utilización'!$B$10:$B$26,0),0) -> 1194.7479 | C9: =HLOOKUP(C$7,'[1]Equilibrio Oferta-Utilización'!$D$10:$O$26,MATCH($A9,'[1]Equilibrio Oferta-Utilización'!$B$10:$B$26,0),0) -> 1541.3326 | D9: =HLOOKUP(D$7,'[1]Equilibrio Oferta-Utilización'!$D$10:$O$26,MATCH($A9,'[1]Equilibrio Oferta-Utilización'!$B$10:$B$26,0),0) -> 1148.422 | E9: =HLOOKUP(E$7,'[1]Equilibrio Oferta-Utilización'!$D$10:$O$26,MATCH($A9,'[1]Equilibrio Oferta-Utilización'!$B$10:$B$26,0),0) -> 2240.933 | F9: =HLOOKUP(F$7,'[1]Equilibrio Oferta-Utilización'!$D$10:$O$26,MATCH($A9,'[1]Equilibrio Oferta-Utilización'!$B$10:$B$26,0),0) -> 2448.268
A10: Oferta total | B10: =HLOOKUP(B$7,'[1]Equilibrio Oferta-Utilización'!$D$10:$O$26,MATCH($A10,'[1]Equilibrio Oferta-Utilización'!$B$10:$B$26,0),0) -> 4989.1614 | C10: =HLOOKUP(C$7,'[1]Equilibrio Oferta-Utilización'!$D$10:$O$26,MATCH($A10,'[1]Equilibrio Oferta-Utilización'!$B$10:$B$26,0),0) -> 6077.9324 | D10: =HLOOKUP(D$7,'[1]Equilibrio Oferta-Utilización'!$D$10:$O$26,MATCH($A10,'[1]Equilibrio Oferta-Utilización'!$B$10:$B$26,0),0) -> 5037.1177 | E10: =HLOOKUP(E$7,'[1]Equilibrio Oferta-Utilización'!$D$10:$O$26,MATCH($A10,'[1]Equilibrio Oferta-Utilización'!$B$10:$B$26,0),0) -> 7197.8352 | F10: =HLOOKUP(F$7,'[1]Equilibrio Oferta-Utilización'!$D$10:$O$26,MATCH($A10,'[1]Equilibrio Oferta-Utilización'!$B$10:$B$26,0),0) -> 7794.134
A11: Consumo intermedio (PC) | B11: =HLOOKUP(B$7,'[1]Equilibrio Oferta-Utilización'!$D$10:$O$26,MATCH($A11,'[1]Equilibrio Oferta-Utilización'!$B$10:$B$26,0),0) -> 147.29109 | C11: =HLOOKUP(C$7,'[1]Equilibrio Oferta-Utilización'!$D$10:$O$26,MATCH($A11,'[1]Equilibrio Oferta-Utilización'!$B$10:$B$26,0),0) -> 155.82214 | D11: =HLOOKUP(D$7,'[1]Equilibrio Oferta-Utilización'!$D$10:$O$26,MATCH($A11,'[1]Equilibrio Oferta-Utilización'!$B$10:$B$26,0),0) -> 136.31543 | E11: =HLOOKUP(E$7,'[1]Equilibrio Oferta-Utilización'!$D$10:$O$26,MATCH($A11,'[1]Equilibrio Oferta-Utilización'!$B$10:$B$26,0),0) -> 211.12398 | F11: =HLOOKUP(F$7,'[1]Equilibrio Oferta-Utilización'!$D$10:$O$26,MATCH($A11,'[1]Equilibrio Oferta-Utilización'!$B$10:$B$26,0),0) -> 232.72227
A12: Consumo final privado (PC) | B12: =HLOOKUP(B$7,'[1]Equilibrio Oferta-Utilización'!$D$10:$O$26,MATCH($A12,'[1]Equilibrio Oferta-Utilización'!$B$10:$B$26,0),0) -> 4549.262 | C12: =HLOOKUP(C$7,'[1]Equilibrio Oferta-Utilización'!$D$10:$O$26,MATCH($A12,'[1]Equilibrio Oferta-Utilización'!$B$10:$B$26,0),0) -> 5655.0099 | D12: =HLOOKUP(D$7,'[1]Equilibrio Oferta-Utilización'!$D$10:$O$26,MATCH($A12,'[1]Equilibrio Oferta-Utilización'!$B$10:$B$26,0),0) -> 4718.3034 | E12: =HLOOKUP(E$7,'[1]Equilibrio Oferta-Utilización'!$D$10:$O$26,MATCH($A12,'[1]Equilibrio Oferta-Utilización'!$B$10:$B$26,0),0) -> 6480.7085 | F12: =HLOOKUP(F$7,'[1]Equilibrio Oferta-Utilización'!$D$10:$O$26,MATCH($A12,'[1]Equilibrio Oferta-Utilización'!$B$10:$B$26,0),0) -> 7052.9349
A13: Variación de existencias (PC) | B13: =HLOOKUP(B$7,'[1]Equilibrio Oferta-Utilización'!$D$10:$O$26,MATCH($A13,'[1]Equilibrio Oferta-Utilización'!$B$10:$B$26,0),0) -> 8.559553 | C13: =HLOOKUP(C$7,'[1]Equilibrio Oferta-Utilización'!$D$10:$O$26,MATCH($A13,'[1]Equilibrio Oferta-Utilización'!$B$10:$B$26,0),0) -> 27.614329 | D13: =HLOOKUP(D$7,'[1]Equilibrio Oferta-Utilización'!$D$10:$O$26,MATCH($A13,'[1]Equilibrio Oferta-Utilización'!$B$10:$B$26,0),0) -> -78.458313 | E13: =HLOOKUP(E$7,'[1]Equilibrio Oferta-Utilización'!$D$10:$O$26,MATCH($A13,'[1]Equilibrio Oferta-Utilización'!$B$10:$B$26,0),0) -> 76.258981 | F13: =HLOOKUP(F$7,'[1]Equilibrio Oferta-Utilización'!$D$10:$O$26,MATCH($A13,'[1]Equilibrio Oferta-Utilización'!$B$10:$B$26,0),0) -> -46.965079
A14: Exportaciones (FOB) | B14: =HLOOKUP(B$7,'[1]Equilibrio Oferta-Utilización'!$D$10:$O$26,MATCH($A14,'[1]Equilibrio Oferta-Utilización'!$B$10:$B$26,0),0) -> 284.0487 | C14: =HLOOKUP(C$7,'[1]Equilibrio Oferta-Utilización'!$D$10:$O$26,MATCH($A14,'[1]Equilibrio Oferta-Utilización'!$B$10:$B$26,0),0) -> 239.48602 | D14: =HLOOKUP(D$7,'[1]Equilibrio Oferta-Utilización'!$D$10:$O$26,MATCH($A14,'[1]Equilibrio Oferta-Utilización'!$B$10:$B$26,0),0) -> 260.95715 | E14: =HLOOKUP(E$7,'[1]Equilibrio Oferta-Utilización'!$D$10:$O$26,MATCH($A14,'[1]Equilibrio Oferta-Utilización'!$B$10:$B$26,0),0) -> 429.74374 | F14: =HLOOKUP(F$7,'[1]Equilibrio Oferta-Utilización'!$D$10:$O$26,MATCH($A14,'[1]Equilibrio Oferta-Utilización'!$B$10:$B$26,0),0) -> 555.44191
A15: Utilización total | B15: =HLOOKUP(B$7,'[1]Equilibrio Oferta-Utilización'!$D$10:$O$26,MATCH($A15,'[1]Equilibrio Oferta-Utilización'!$B$10:$B$26,0),0) -> 4989.1614 | C15: =HLOOKUP(C$7,'[1]Equilibrio Oferta-Utilización'!$D$10:$O$26,MATCH($A15,'[1]Equilibrio Oferta-Utilización'!$B$10:$B$26,0),0) -> 6077.9324 | D15: =HLOOKUP(D$7,'[1]Equilibrio Oferta-Utilización'!$D$10:$O$26,MATCH($A15,'[1]Equilibrio Oferta-Utilización'!$B$10:$B$26,0),0) -> 5037.1177 | E15: =HLOOKUP(E$7,'[1]Equilibrio Oferta-Utilización'!$D$10:$O$26,MATCH($A15,'[1]Equilibrio Oferta-Utilización'!$B$10:$B$26,0),0) -> 7197.8352 | F15: =HLOOKUP(F$7,'[1]Equilibrio Oferta-Utilización'!$D$10:$O$26,MATCH($A15,'[1]Equilibrio Oferta-Utilización'!$B$10:$B$26,0),0) -> 7794.134
A18: 1.1 · Verificación contable
A19: Oferta total 2024 | B19: =F10 -> 7794.134
A20: Utilización total 2024 | B20: =F15 -> 7794.134
A21: Diferencia | B21: =B19-B20 -> 0 | D21: ¿Equilibra? | E21: =IF(ABS(B21)<0.01,"Sí","Revisar datos") -> Sí
A24: 1.1 Interpretación económica. ¿Qué significa que la oferta total sea igual a la utilización total?
N28: 15 | P28: =N28*1000000 -> 15000000 | Q28: =P28/P29 -> 37500
P29: 400
A30: 1.2 ¿Qué partida utilizaría como mejor aproximación inicial al mercado nacional observado de ANDAR GT? Justifique en no más de cinco líneas.
K31: INGRESO | L31: = | N31: Q
K32: P

Sheet Etapa2_Evolucion
A1: ETAPA 2 · EVOLUCIÓN DEL MERCADO
A2: Consumo final privado de calzado · Serie 2013–2024
A7: Año | B7: Consumo final privado (millones de Q) | C7: Crecimiento anual
A8: 2013 | B8: =Etapa1_Datos!B12 -> 4549.262
A9: 2014 | B9: 4828.8815 | C9: =IF(OR(B9="",B8=""),"",B9/B8-1) -> 0.061464799
A10: 2015 | B10: 5085.5369 | C10: =IF(OR(B10="",B9=""),"",B10/B9-1) -> 0.053150066
A11: 2016 | B11: 5247.8107 | C11: =IF(OR(B11="",B10=""),"",B11/B10-1) -> 0.031908898
A12: 2017 | B12: 5348.2195 | C12: =IF(OR(B12="",B11=""),"",B12/B11-1) -> 0.019133455
A13: 2018 | B13: 5541.2928 | C13: =IF(OR(B13="",B12=""),"",B13/B12-1) -> 0.036100475
A14: 2019 | B14: =Etapa1_Datos!C12 -> 5655.0099 | C14: =IF(OR(B14="",B13=""),"",B14/B13-1) -> 0.020521764
A15: 2020 | B15: =Etapa1_Datos!D12 -> 4718.3034 | C15: =IF(OR(B15="",B14=""),"",B15/B14-1) -> -0.16564188
A16: 2021 | B16: 5492.1077 | C16: =IF(OR(B16="",B15=""),"",B16/B15-1) -> 0.16400054
A17: 2022 | B17: 6063.1149 | C17: =IF(OR(B17="",B16=""),"",B17/B16-1) -> 0.10396869
A18: 2023 | B18: =Etapa1_Datos!E12 -> 6480.7085 | C18: =IF(OR(B18="",B17=""),"",B18/B17-1) -> 0.068874423
A19: 2024 | B19: =Etapa1_Datos!F12 -> 7052.9349 | C19: =IF(OR(B19="",B18=""),"",B19/B18-1) -> 0.088296888
A22: Indicadores de control
A23: Crecimiento 2019 → 2020 | B23: =IF(OR(B14="",B15=""),"",B15/B14-1) -> -0.16564188
A24: Crecimiento 2020 → 2021 | B24: =IF(OR(B15="",B16=""),"",B16/B15-1) -> 0.16400054
A25: Crecimiento 2023 → 2024 | B25: =IF(OR(B18="",B19=""),"",B19/B18-1) -> 0.088296888
A26: TCMA 2013 → 2024 | B26: =IF(OR(B8="",B19=""),"",(B19/B8)^(1/11)-1) -> 0.040666849
A29: 2.1 ¿Puede interpretarse el crecimiento del valor monetario como crecimiento de la cantidad de pares demandados? Explique.
A36: Identifique el principal quiebre de la serie y explique qué precaución tendría al proyectar la demanda futura.

Sheet Etapa3_Mercado
A1: ETAPA 3 · DEL MERCADO NACIONAL AL MERCADO OBJETIVO
A2: Embudo de mercado · año base 2024
A6: Supuestos académicos del caso
A7: Participación segmento casual-deportivo gama media | B7: 0.3 | C7: Supuesto del caso | F7: MERCADO NACIONAL
A8: Participación territorio / canales accesibles | B8: 0.25 | C8: Supuesto del caso
A9: Precio neto promedio por par (Q) | B9: 420 | C9: Supuesto del caso | F9: =B17 -> 7052.9349
A10: Captura escenario conservador | B10: 0.015 | C10: Supuesto del caso
A11: Captura escenario base | B11: 0.02 | C11: Supuesto del caso | F11: MERCADO RELEVANTE
A12: Captura escenario optimista | B12: 0.03 | C12: Supuesto del caso
A13: Capacidad máxima primer año (pares) | B13: 30000 | C13: Supuesto del caso | F13: =B18 -> 2115.8805
F15: MERCADO OBJETIVO
A16: Embudo de mercado
A17: Mercado nacional observado | B17: =Etapa1_Datos!F12 -> 7052.9349 | C17: Consumo final privado 2024 | F17: =B19 -> 528.97011
A18: Mercado relevante | B18: =B17*B7 -> 2115.8805 | C18: Mercado nacional × segmento
A19: Mercado objetivo | B19: =B18*B8 -> 528.97011 | C19: Mercado relevante × territorio/canal
A23: 3.1 Explique la diferencia entre mercado nacional, mercado relevante y mercado objetivo. ¿Por qué sería incorrecto utilizar directamente el consumo nacional como ventas esperadas?
A31: Comentarios sobre la razonabilidad de los supuestos de segmentación y cobertura.

Sheet Etapa4_Demanda
A1: ETAPA 4 · DEMANDA CAPTURABLE
A2: Tres escenarios de penetración de mercado
A7: Escenario | B7: Captura | C7: Ventas potenciales (millones de Q) | D7: Pares demandados
A8: Conservador | B8: =Etapa3_Mercado!B10 -> 0.015 | C8: =Etapa3_Mercado!$B$19*B8 -> 7.9345517 | D8: =IF(C8="","",C8*1000000/Etapa3_Mercado!B9) -> 18891.79
A9: Base | B9: =Etapa3_Mercado!B11 -> 0.02 | C9: =Etapa3_Mercado!B19*B9 -> 10.579402 | D9: =IF(C9="","",C9*1000000/Etapa3_Mercado!B9) -> 25189.053
A10: Optimista | B10: =Etapa3_Mercado!B12 -> 0.03 | C10: =Etapa3_Mercado!B19*B10 -> 15.869103 | D10: =IF(C10="","",C10*1000000/Etapa3_Mercado!B9) -> 37783.58
A13: Datos de referencia
A14: Mercado objetivo (millones de Q) | B14: =Etapa3_Mercado!B19 -> 528.97011
A15: Precio promedio por par | B15: =Etapa3_Mercado!B9 -> 420
A18: 4.1 Sensibilidad. ¿Qué variable tiene mayor capacidad de alterar la demanda estimada? Distinga entre parámetros sustentados por información oficial y supuestos comerciales.
A26: Comentarios sobre la razonabilidad de los escenarios de captura.

Sheet Etapa5_Capacidad
A1: ETAPA 5 · MERCADO VS. CAPACIDAD PRODUCTIVA
A2: La demanda potencial no siempre puede convertirse en ventas factibles
A7: Escenario | B7: Pares demandados | C7: Capacidad máxima | D7: Pares factibles | E7: Utilización capacidad | F7: Ventas factibles (Q)
A8: Conservador | B8: =Etapa4_Demanda!D8 -> 18891.79 | C8: =Etapa3_Mercado!B13 -> 30000 | D8: =MIN(B8,C8) -> 18891.79 | E8: =IF(C8=0,"",D8/C8) -> 0.62972633 | F8: =D8*Etapa3_Mercado!B9 -> 7934551.7
A9: Base | B9: =Etapa4_Demanda!D9 -> 25189.053 | C9: =Etapa3_Mercado!B13 -> 30000 | D9: =MIN(B9,C9) -> 25189.053 | E9: =IF(C9=0,"",D9/C9) -> 0.8396351 | F9: =D9*Etapa3_Mercado!B9 -> 10579402
A10: Optimista | B10: =Etapa4_Demanda!D10 -> 37783.58 | C10: =Etapa3_Mercado!B13 -> 30000 | D10: =MIN(B10,C10) -> 30000 | E10: =IF(C10=0,"",D10/C10) -> 1 | F10: =D10*Etapa3_Mercado!B9 -> 12600000
A31: 5.1 ¿En cuál escenario la restricción principal proviene del mercado y en cuál de la capacidad productiva? ¿Qué implicación tendría para el diseño técnico del proyecto?
A39: Conclusión de la etapa. Resuma la relación entre demanda estimada, capacidad instalada y ventas factibles.

Sheet Etapa6_Informe
A1: ETAPA 6 · RECOMENDACIÓN AL COMITÉ DE INVERSIÓN
A2: Síntesis ejecutiva del estudio preliminar de mercado
A6: Resumen cuantitativo
A7: Mercado nacional observado (millones de Q) | D7: =Etapa3_Mercado!B17 -> 7052.9349
A8: Mercado objetivo (millones de Q) | D8: =Etapa3_Mercado!B19 -> 528.97011
A9: Pares demandados · conservador | D9: =Etapa4_Demanda!D8 -> 18891.79
A10: Pares demandados · base | D10: =Etapa4_Demanda!D9 -> 25189.053
A11: Pares demandados · optimista | D11: =Etapa4_Demanda!D10 -> 37783.58
A12: Capacidad máxima primer año | D12: =Etapa3_Mercado!B13 -> 30000
A15: Recomendación ejecutiva · máximo 250 palabras
F28: Conteo aproximado de palabras | H28: =IF(A16="","",LEN(TRIM(A16))-LEN(SUBSTITUTE(TRIM(A16)," ",""))+1)
A31: Discusión final · límites de la estimación
A32: 1. ¿Qué información adicional solicitaría para convertir esta aproximación en un estudio de mercado completo?
A37: 2. ¿Qué cambiaría si el proyecto produjera calzado de seguridad para empresas en vez de calzado casual para hogares?
A42: 3. ¿Por qué no sería correcto interpretar las importaciones como mercado disponible para sustituir ni proyectar únicamente con la TCMA 2013–2024?
A47: 4. ¿Cómo se trasladaría una sobreestimación de la demanda hacia los ingresos, flujo de caja, VAN y TIR?
A53: Fuente y declaración de supuestos
A54: Fuente estadística: Banco de Guatemala, Equilibrio de oferta y utilización, producto P062. Sitio institucional: https://www.banguat.gob.gt/ Los porcentajes de segmentación, cobertura, captura, precio promedio y capacidad instalada son supuestos académicos del caso ANDAR GT, S.A.
